mugennoshared/model/db.py
mugennoshared/model/genre.py
mugennoshared/model/interfaces.py
mugennoshared/model/manga.py
mugennoshared-0.1.3.dist-info/METADATA
mugennoshared-0.1.3.dist-info/WHEEL
mugennoshared-0.1.3.dist-info/RECORD
