Metadata-Version: 2.3
Name: mugennoshared
Version: 0.1.3
Summary: Shared lib for the mugen project. Components used by two or more of the mugen ecossystem.
License: GPLv3
Author: Kyamel
Author-email: lcamelo200@gmail.com
Requires-Python: >=3.12
Classifier: License :: Other/Proprietary License
Classifier: Programming Language :: Python :: 3
Classifier: Programming Language :: Python :: 3.12
Classifier: Programming Language :: Python :: 3.13
Requires-Dist: SQLAlchemy (>=2.0.40,<3.0.0)
Requires-Dist: numpy (>=2.2.5,<3.0.0)
